geotechnicalprofile/__init__.py
geotechnicalprofile/__main__.py
geotechnicalprofile/cli.py
geotechnicalprofile/gef_helpers.py
geotechnicalprofile/gp_datastore.py
geotechnicalprofile/plot_helpers.py
geotechnicalprofile-0.3.0.dist-info/METADATA
geotechnicalprofile-0.3.0.dist-info/RECORD
geotechnicalprofile-0.3.0.dist-info/WHEEL
geotechnicalprofile-0.3.0.dist-info/entry_points.txt
geotechnicalprofile-0.3.0.dist-info/top_level.txt
