Metadata-Version: 2.1
Name: geotechnicalprofile
Version: 0.3.0
Summary: Load, manage, and plot geotechnical data, including GEF and DTS measurements
Home-page: https://github.com/bdestombe/python-geotechnical-profile
Author: Bas des Tombe
Author-email: bdestombe@gmail.com
License: BSD 3-Clause License
Platform: UNKNOWN
Classifier: Development Status :: 5 - Production/Stable
Classifier: Intended Audience :: Developers
Classifier: License :: OSI Approved :: BSD License
Classifier: Operating System :: Unix
Classifier: Operating System :: POSIX
Classifier: Operating System :: Microsoft :: Windows
Classifier: Programming Language :: Python
Classifier: Programming Language :: Python :: 2.7
Classifier: Programming Language :: Python :: 3
Classifier: Programming Language :: Python :: 3.4
Classifier: Programming Language :: Python :: 3.5
Classifier: Programming Language :: Python :: 3.6
Classifier: Programming Language :: Python :: 3.7
Classifier: Programming Language :: Python :: Implementation :: CPython
Classifier: Programming Language :: Python :: Implementation :: PyPy
Classifier: Topic :: Utilities
Requires-Dist: numpy
Requires-Dist: xarray
Requires-Dist: pyyaml
Requires-Dist: xmltodict
Requires-Dist: scipy
Requires-Dist: statsmodels
Requires-Dist: nbsphinx
Requires-Dist: dask
Requires-Dist: toolz
Requires-Dist: matplotlib
Requires-Dist: netCDF4
